medmij/__init__.py
medmij/gnl.py
medmij/gnl.xsd
medmij/oauthclientlist.py
medmij/oauthclientlist.xsd
medmij/whitelist.py
medmij/whitelist.xsd
medmij/xml_utils.py
medmij/zal.py
medmij/zal.xsd
medmij_lists/__init__.py
medmij_lists/gnl.py
medmij_lists/gnl.xsd
medmij_lists/oauthclientlist.py
medmij_lists/oauthclientlist.xsd
medmij_lists/whitelist.py
medmij_lists/whitelist.xsd
medmij_lists/xml_utils.py
medmij_lists/zal.py
medmij_lists/zal.xsd
medmij_lists-0.1.0.dist-info/LICENSE.txt
medmij_lists-0.1.0.dist-info/METADATA
medmij_lists-0.1.0.dist-info/WHEEL
medmij_lists-0.1.0.dist-info/top_level.txt
medmij_lists-0.1.0.dist-info/zip-safe
medmij_lists-0.1.0.dist-info/RECORD
