Metadata-Version: 2.1
Name: medmij-lists
Version: 0.1.0
Summary: Python implementation of de MedMij ZAL, OCL, Whitelist and GNL
Home-page: https://github.com/GidsOpenStandaarden/OpenPGO-Medmij-ImplementatieBouwstenen-Python
License: UNKNOWN
Platform: UNKNOWN
Requires-Dist: lxml
